README.md
setup.py
keap/Keap.py
keap/KeapToken.py
keap/KeapTokenStorage.py
keap/__init__.py
keap_auth_python.egg-info/PKG-INFO
keap_auth_python.egg-info/SOURCES.txt
keap_auth_python.egg-info/dependency_links.txt
keap_auth_python.egg-info/entry_points.txt
keap_auth_python.egg-info/requires.txt
keap_auth_python.egg-info/top_level.txt