Metadata-Version: 2.1
Name: keap-auth-python
Version: 0.2
Summary: Python SDK for Keap API
Home-page: https://bitbucket.org/theapiguys/keap-python
Author: Brandon@TheAPIGuys
Author-email: brandon@theapiguys.com
License: UNKNOWN
Platform: UNKNOWN
